pulseclient/__init__.py
pulseclient/lib.py
pulseclient/start_client.py
pulseclient-0.1.0.dist-info/LICENSE.txt
pulseclient-0.1.0.dist-info/METADATA
pulseclient-0.1.0.dist-info/WHEEL
pulseclient-0.1.0.dist-info/entry_points.txt
pulseclient-0.1.0.dist-info/top_level.txt
pulseclient-0.1.0.dist-info/RECORD
