Metadata-Version: 2.1
Name: pulseclient
Version: 0.1.0
Summary: A Python client for communication between Pulseq interpreter and Pulseq design server.
Home-page: https://github.com/INFN-MRI/pulseclient
Author: Matteo Cencini
Author-email: Matteo Cencini <matteo.cencini@gmail.com>
Project-URL: Homepage, https://github.com/INFN-MRI/pulseclient
Project-URL: Bug Reports, https://github.com/INFN-MRI/pulseclient/issues
Project-URL: Source, https://github.com/INFN-MRI/pulseclient
Keywords: pulseq,mri,sequence-design,pulse-sequences,mri-sequences
Classifier: Development Status :: 3 - Alpha
Classifier: Intended Audience :: Developers
Classifier: License :: OSI Approved :: MIT License
Classifier: Programming Language :: Python :: 2.6
Classifier: Programming Language :: Python :: 2.7
Classifier: Programming Language :: Python :: 3.0
Classifier: Programming Language :: Python :: 3.1
Classifier: Programming Language :: Python :: 3.2
Classifier: Programming Language :: Python :: 3.3
Classifier: Programming Language :: Python :: 3.4
Classifier: Programming Language :: Python :: 3.5
Classifier: Programming Language :: Python :: 3.6
Classifier: Programming Language :: Python :: 3.7
Classifier: Programming Language :: Python :: 3.8
Classifier: Programming Language :: Python :: 3.9
Classifier: Programming Language :: Python :: 3.10
Classifier: Programming Language :: Python :: 3.11
Classifier: Programming Language :: Python :: 3.12
Requires-Python: >=2.6
License-File: LICENSE.txt
Provides-Extra: dev
Requires-Dist: black; extra == "dev"
Requires-Dist: isort; extra == "dev"
